hypercore_crypto/__init__.py
hypercore_crypto/crypto.py
hypercore_crypto-0.0.1a4.dist-info/LICENSE
hypercore_crypto-0.0.1a4.dist-info/WHEEL
hypercore_crypto-0.0.1a4.dist-info/METADATA
hypercore_crypto-0.0.1a4.dist-info/RECORD
